dfapi/__init__.py
dfapi/dfapi.py
dfapi/example_insert_data.py
dfapi/example_pi_log.py
dfapi/example_read_data.py
dfapi/examples.py
dfapi-0.1.2.dist-info/METADATA
dfapi-0.1.2.dist-info/WHEEL
dfapi-0.1.2.dist-info/top_level.txt
dfapi-0.1.2.dist-info/RECORD
